athlib/__init__.py
athlib/athlon_score.py
athlib/bulgarian_score.py
athlib/codes.py
athlib/exceptions.py
athlib/highjump.py
athlib/hungarian_score.py
athlib/implements.py
athlib/jsondict.py
athlib/qkids_score.py
athlib/sportshall_score.py
athlib/tyrving_score.py
athlib/utils.py
athlib/uka/__init__.py
athlib/uka/agegroups.py
athlib/wma/__init__.py
athlib/wma/agegrader.py
athlib/wma/create_2023_data.py
athlib/wma/mldr-data-2020.json
athlib/wma/wma-athlons-data.json
athlib/wma/wma-data-2015.json
athlib/wma/wma-data-2023.json
athlib/wma/wma-inputs-2023.json
athlib-0.9.3.dist-info/LICENSE
athlib-0.9.3.dist-info/METADATA
athlib-0.9.3.dist-info/WHEEL
athlib-0.9.3.dist-info/top_level.txt
athlib-0.9.3.dist-info/RECORD
