Metadata-Version: 2.1
Name: athlib
Version: 0.9.3
Summary: Utilities for track and field athletics
Home-page: https://github.com/openath/athlib
Author: Andy Robinson and others
Author-email: andy@reportlab.com
License: Apache
Keywords: athletics track field
Platform: UNKNOWN
Classifier: Development Status :: 5 - Production/Stable
Classifier: Intended Audience :: Developers
Classifier: License :: OSI Approved :: Apache Software License
Classifier: Topic :: Utilities
Classifier: Programming Language :: Python :: 2.7
Classifier: Programming Language :: Python :: 3.6
Classifier: Programming Language :: Python :: 3.7
Classifier: Programming Language :: Python :: 3.8
Classifier: Programming Language :: Python :: 3.9
Requires-Python: >=2.7
License-File: LICENSE
Requires-Dist: jsonschema >=2.6.0
Requires-Dist: python-dateutil
